pycnab240/__init__.py
pycnab240/errors.py
pycnab240/file.py
pycnab240/record.py
pycnab240/utils.py
pycnab240/bancos/__init__.py
pycnab240/bancos/bradesco/__init__.py
pycnab240/bancos/bradesco/specs/header_arquivo.json
pycnab240/bancos/bradesco/specs/header_lote.json
pycnab240/bancos/bradesco/specs/segmento_a.json
pycnab240/bancos/bradesco/specs/segmento_b.json
pycnab240/bancos/bradesco/specs/segmento_g.json
pycnab240/bancos/bradesco/specs/segmento_h.json
pycnab240/bancos/bradesco/specs/segmento_j.json
pycnab240/bancos/bradesco/specs/segmento_j52.json
pycnab240/bancos/bradesco/specs/segmento_n.json
pycnab240/bancos/bradesco/specs/segmento_o.json
pycnab240/bancos/bradesco/specs/segmento_w.json
pycnab240/bancos/bradesco/specs/segmento_z.json
pycnab240/bancos/bradesco/specs/trailer_arquivo.json
pycnab240/bancos/bradesco/specs/trailer_lote.json
pycnab240/bancos/itau/__init__.py
pycnab240/bancos/itau/specs/header_arquivo.json
pycnab240/bancos/itau/specs/header_lote.json
pycnab240/bancos/itau/specs/segmento_a.json
pycnab240/bancos/itau/specs/segmento_a_nf.json
pycnab240/bancos/itau/specs/segmento_b.json
pycnab240/bancos/itau/specs/segmento_b_fgts.json
pycnab240/bancos/itau/specs/segmento_c.json
pycnab240/bancos/itau/specs/segmento_d.json
pycnab240/bancos/itau/specs/segmento_e.json
pycnab240/bancos/itau/specs/segmento_f.json
pycnab240/bancos/itau/specs/segmento_j.json
pycnab240/bancos/itau/specs/segmento_j52.json
pycnab240/bancos/itau/specs/segmento_n.json
pycnab240/bancos/itau/specs/segmento_o.json
pycnab240/bancos/itau/specs/segmento_w.json
pycnab240/bancos/itau/specs/segmento_z.json
pycnab240/bancos/itau/specs/trailer_arquivo.json
pycnab240/bancos/itau/specs/trailer_lote.json
pycnab240/bancos/itau/specs/trailer_lote_tributos.json
pycnab240/bancos/santander/__init__.py
pycnab240/bancos/santander/specs/header_arquivo.json
pycnab240/bancos/santander/specs/header_lote.json
pycnab240/bancos/santander/specs/segmento_a.json
pycnab240/bancos/santander/specs/segmento_b.json
pycnab240-0.1.28.dist-info/LICENSE
pycnab240-0.1.28.dist-info/METADATA
pycnab240-0.1.28.dist-info/WHEEL
pycnab240-0.1.28.dist-info/top_level.txt
pycnab240-0.1.28.dist-info/RECORD
