Metadata-Version: 2.1
Name: pycnab240
Version: 0.1.28
Summary: Lib para gerar arquivo CNAB 240 - Integração bancária
Home-page: https://github.com/Trust-Code/PyTrustCnab240
Author: Trustcode
Author-email: suporte@trustcode.com.br
License: MIT
Download-URL: https://github.com/Trust-Code/PyTrustCnab240
Keywords: cnab,cnab240,pycnab
Platform: any
Classifier: Development Status :: 3 - Alpha
Classifier: Environment :: Plugins
Classifier: Intended Audience :: Developers
Classifier: Operating System :: OS Independent
Classifier: Programming Language :: Python
Classifier: Programming Language :: Python :: 3.6
Classifier: Programming Language :: Python :: 3.5
Classifier: Programming Language :: Python :: 3.4
Classifier: Programming Language :: Python :: 2.7
Classifier: Topic :: Software Development :: Libraries :: Python Modules
Requires-Dist: setuptools-git (==1.1)
Requires-Dist: future
